requests_abc/__init__.py
requests_abc/requests_abc.py
requests_abc-0.4.0.dist-info/METADATA
requests_abc-0.4.0.dist-info/WHEEL
requests_abc-0.4.0.dist-info/top_level.txt
requests_abc-0.4.0.dist-info/RECORD
